NVLib/__init__.py
NVLib/cli.py
NVLib/Components/__init__.py
NVLib/Components/Audio/TextToSpeech.py
NVLib/Components/Audio/__init__.py
NVLib/Components/Authentication/FirebaseAuth.py
NVLib/Components/Authentication/__init__.py
NVLib/Components/Database/Mariadb.py
NVLib/Components/Database/Tinydb.py
NVLib/Components/Database/__init__.py
NVLib/Components/GUI/AutoGUI.py
NVLib/Components/GUI/__init__.py
NVLib/Components/VisualRec/FLRH.py
NVLib/Components/VisualRec/HandTracker.py
NVLib/Components/VisualRec/__init__.py
nvlib_sn-3.0.0.dist-info/METADATA
nvlib_sn-3.0.0.dist-info/WHEEL
nvlib_sn-3.0.0.dist-info/entry_points.txt
nvlib_sn-3.0.0.dist-info/top_level.txt
nvlib_sn-3.0.0.dist-info/RECORD
