Metadata-Version: 2.4
Name: nvlib-sn
Version: 3.0.0
Summary: Making programming easy for everyone | Windows-only build
Home-page: https://github.com/saineela/NVLib
Author: Sai Neela
Author-email: saiathulithn@gmail.com
Classifier: Development Status :: 3 - Alpha
Classifier: Intended Audience :: Developers
Classifier: License :: CC0 1.0 Universal (CC0 1.0) Public Domain Dedication
Classifier: Programming Language :: Python :: 3
Classifier: Operating System :: Microsoft :: Windows
Classifier: Topic :: Software Development :: Libraries
Requires-Python: >=3.10,<3.13
Requires-Dist: edge-tts==7.2.3
Requires-Dist: firebase-admin==7.1.0
Requires-Dist: mariadb==1.1.14
Requires-Dist: Kivy==2.3.1
Requires-Dist: kivymd==1.2.0
Requires-Dist: opencv-python==4.12.0.88
Requires-Dist: mediapipe==0.10.14
Requires-Dist: pyinstaller==6.16.0
Dynamic: author
Dynamic: author-email
Dynamic: classifier
Dynamic: description
Dynamic: description-content-type
Dynamic: home-page
Dynamic: requires-dist
Dynamic: requires-python
Dynamic: summary
